[{"COUNTRY_CODE":"FI","NUTS3":"FI194","LAU1":"146","LAU2":"005","_CHANGE":"no","NAME1":"Alajärvi","NAME2":"Alajärvi","POP":"10006","AREA":"1056740000"},{"COUNTRY_CODE":"FI","NUTS3":"FI1D6","LAU1":"177","LAU2":"009","_CHANGE":"no","NAME1":"Alavieska","NAME2":"Alavieska","POP":"2687","AREA":"253020000"},{"COUNTRY_CODE":"FI","NUTS3":"FI194","LAU1":"144","LAU2":"010","_CHANGE":"no","NAME1":"Alavus","NAME2":"Alavus","POP":"12044","AREA":"1151460000"},{"COUNTRY_CODE":"FI","NUTS3":"FI1C3","LAU1":"071","LAU2":"016","_CHANGE":"no","NAME1":"Asikkala","NAME2":"Asikkala","POP":"8287","AREA":"755550000"},{"COUNTRY_CODE":"FI","NUTS3":"FI1B1","LAU1":"015","LAU2":"018","_CHANGE":"no","NAME1":"Askola","NAME2":"Askola","POP":"5104","AREA":"218030000"},{"COUNTRY_CODE":"FI","NUTS3":"FI1C1","LAU1":"025","LAU2":"019","_CHANGE":"no","NAME1":"Aura","NAME2":"Aura","POP":"3986","AREA":"95580000"},{"COUNTRY_CODE":"FI","NUTS3":"FI197","LAU1":"063","LAU2":"020","_CHANGE":"no","NAME1":"Akaa","NAME2":"Akaa","POP":"17043","AREA":"314390000"},{"COUNTRY_CODE":"FI","NUTS3":"FI200","LAU1":"213","LAU2":"035","_CHANGE":"no","NAME1":"Brändö","NAME2":"Brändö","POP":"470","AREA":"1643060000"},{"COUNTRY_CODE":"FI","NUTS3":"FI200","LAU1":"212","LAU2":"043","_CHANGE":"no","NAME1":"Eckerö","NAME2":"Eckerö","POP":"935","AREA":"752670000"},{"COUNTRY_CODE":"FI","NUTS3":"FI1D1","LAU1":"103","LAU2":"046","_CHANGE":"no","NAME1":"Enonkoski","NAME2":"Enonkoski","POP":"1473","AREA":"419190000"},{"COUNTRY_CODE":"FI","NUTS3":"FI1D7","LAU1":"196","LAU2":"047","_CHANGE":"no","NAME1":"Enontekiö","NAME2":"Enontekis","POP":"1861","AREA":"8391350000"},{"COUNTRY_CODE":"FI","NUTS3":"FI1B1","LAU1":"011","LAU2":"049","_CHANGE":"no","NAME1":"Espoo","NAME2":"Esbo","POP":"269802","AREA":"528030000"},{"COUNTRY_CODE":"FI","NUTS3":"FI196","LAU1":"041","LAU2":"050","_CHANGE":"no","NAME1":"Eura","NAME2":"Eura","POP":"12128","AREA":"630200000"},{"COUNTRY_CODE":"FI","NUTS3":"FI196","LAU1":"041","LAU2":"051","_CHANGE":"no","NAME1":"Eurajoki","NAME2":"Euraåminne","POP":"5938","AREA":"643780000"},{"COUNTRY_CODE":"FI","NUTS3":"FI194","LAU1":"146","LAU2":"052","_CHANGE":"no","NAME1":"Evijärvi","NAME2":"Evijärvi","POP":"2576","AREA":"390710000"},{"COUNTRY_CODE":"FI","NUTS3":"FI200","LAU1":"212","LAU2":"060","_CHANGE":"no","NAME1":"Finström","NAME2":"Finström","POP":"2522","AREA":"172490000"},{"COUNTRY_CODE":"FI","NUTS3":"FI1C2","LAU1":"053","LAU2":"061","_CHANGE":"no","NAME1":"Forssa","NAME2":"Forssa","POP":"17422","AREA":"253390000"},{"COUNTRY_CODE":"FI","NUTS3":"FI200","LAU1":"213","LAU2":"062","_CHANGE":"no","NAME1":"Föglö","NAME2":"Föglö","POP":"554","AREA":"1869070000"},{"COUNTRY_CODE":"FI","NUTS3":"FI200","LAU1":"212","LAU2":"065","_CHANGE":"no","NAME1":"Geta","NAME2":"Geta","POP":"500","AREA":"605980000"},{"COUNTRY_CODE":"FI","NUTS3":"FI1D6","LAU1":"176","LAU2":"069","_CHANGE":"no","NAME1":"Haapajärvi","NAME2":"Haapajärvi","POP":"7438","AREA":"789110000"},{"COUNTRY_CODE":"FI","NUTS3":"FI1D6","LAU1":"175","LAU2":"071","_CHANGE":"no","NAME1":"Haapavesi","NAME2":"Haapavesi","POP":"7167","AREA":"1086110000"},{"COUNTRY_CODE":"FI","NUTS3":"FI1D6","LAU1":"171","LAU2":"072","_CHANGE":"no","NAME1":"Hailuoto","NAME2":"Karlö","POP":"993","AREA":"1082700000"},{"COUNTRY_CODE":"FI","NUTS3":"FI1D5","LAU1":"161","LAU2":"074","_CHANGE":"no","NAME1":"Halsua","NAME2":"Halsua","POP":"1225","AREA":"428340000"},{"COUNTRY_CODE":"FI","NUTS3":"FI1C4","LAU1":"082","LAU2":"075","_CHANGE":"no","NAME1":"Hamina","NAME2":"Fredrikshamn","POP":"20851","AREA":"1155120000"},{"COUNTRY_CODE":"FI","NUTS3":"FI200","LAU1":"212","LAU2":"076","_CHANGE":"no","NAME1":"Hammarland","NAME2":"Hammarland","POP":"1537","AREA":"1224180000"},{"COUNTRY_CODE":"FI","NUTS3":"FI193","LAU1":"131","LAU2":"077","_CHANGE":"no","NAME1":"Hankasalmi","NAME2":"Hankasalmi","POP":"5240","AREA":"687750000"},{"COUNTRY_CODE":"FI","NUTS3":"FI1B1","LAU1":"014","LAU2":"078","_CHANGE":"no","NAME1":"Hanko","NAME2":"Hangö","POP":"8864","AREA":"799990000"},{"COUNTRY_CODE":"FI","NUTS3":"FI196","LAU1":"043","LAU2":"079","_CHANGE":"no","NAME1":"Harjavalta","NAME2":"Harjavalta","POP":"7296","AREA":"127740000"},{"COUNTRY_CODE":"FI","NUTS3":"FI1C3","LAU1":"071","LAU2":"081","_CHANGE":"no","NAME1":"Hartola","NAME2":"Hartola","POP":"2982","AREA":"675380000"},{"COUNTRY_CODE":"FI","NUTS3":"FI1C2","LAU1":"051","LAU2":"082","_CHANGE":"no","NAME1":"Hattula","NAME2":"Hattula","POP":"9747","AREA":"427390000"},{"COUNTRY_CODE":"FI","NUTS3":"FI1C2","LAU1":"052","LAU2":"086","_CHANGE":"no","NAME1":"Hausjärvi","NAME2":"Hausjärvi","POP":"8729","AREA":"398780000"},{"COUNTRY_CODE":"FI","NUTS3":"FI1D1","LAU1":"103","LAU2":"090","_CHANGE":"no","NAME1":"Heinävesi","NAME2":"Heinävesi","POP":"3574","AREA":"1319580000"},{"COUNTRY_CODE":"FI","NUTS3":"FI1B1","LAU1":"011","LAU2":"091","_CHANGE":"no","NAME1":"Helsinki","NAME2":"Helsingfors","POP":"628208","AREA":"715480000"},{"COUNTRY_CODE":"FI","NUTS3":"FI1B1","LAU1":"011","LAU2":"092","_CHANGE":"no","NAME1":"Vantaa","NAME2":"Vanda","POP":"214605","AREA":"240340000"},{"COUNTRY_CODE":"FI","NUTS3":"FI1D1","LAU1":"101","LAU2":"097","_CHANGE":"no","NAME1":"Hirvensalmi","NAME2":"Hirvensalmi","POP":"2290","AREA":"746590000"},{"COUNTRY_CODE":"FI","NUTS3":"FI1C3","LAU1":"071","LAU2":"098","_CHANGE":"1/1/16","NAME1":"Hollola","NAME2":"Hollola","POP":"23915","AREA":"727470000"},{"COUNTRY_CODE":"FI","NUTS3":"FI196","LAU1":"044","LAU2":"099","_CHANGE":"no","NAME1":"Honkajoki","NAME2":"Honkajoki","POP":"1793","AREA":"333140000"},{"COUNTRY_CODE":"FI","NUTS3":"FI196","LAU1":"043","LAU2":"102","_CHANGE":"no","NAME1":"Huittinen","NAME2":"Huittinen","POP":"10473","AREA":"539590000"},{"COUNTRY_CODE":"FI","NUTS3":"FI1C2","LAU1":"053","LAU2":"103","_CHANGE":"no","NAME1":"Humppila","NAME2":"Humppila","POP":"2388","AREA":"148600000"},{"COUNTRY_CODE":"FI","NUTS3":"FI1D4","LAU1":"181","LAU2":"105","_CHANGE":"no","NAME1":"Hyrynsalmi","NAME2":"Hyrynsalmi","POP":"2422","AREA":"1521370000"},{"COUNTRY_CODE":"FI","NUTS3":"FI1B1","LAU1":"011","LAU2":"106","_CHANGE":"no","NAME1":"Hyvinkää","NAME2":"Hyvinge","POP":"46463","AREA":"336770000"},{"COUNTRY_CODE":"FI","NUTS3":"FI197","LAU1":"064","LAU2":"108","_CHANGE":"no","NAME1":"Hämeenkyrö","NAME2":"Tavastkyro","POP":"10667","AREA":"505100000"},{"COUNTRY_CODE":"FI","NUTS3":"FI1C2","LAU1":"051","LAU2":"109","_CHANGE":"no","NAME1":"Hämeenlinna","NAME2":"Tavastehus","POP":"68011","AREA":"2031520000"},{"COUNTRY_CODE":"FI","NUTS3":"FI1C3","LAU1":"071","LAU2":"111","_CHANGE":"no","NAME1":"Heinola","NAME2":"Heinola","POP":"19575","AREA":"839280000"},{"COUNTRY_CODE":"FI","NUTS3":"FI1D6","LAU1":"173","LAU2":"139","_CHANGE":"no","NAME1":"Ii","NAME2":"Ii","POP":"9663","AREA":"2809310000"},{"COUNTRY_CODE":"FI","NUTS3":"FI1D2","LAU1":"111","LAU2":"140","_CHANGE":"no","NAME1":"Iisalmi","NAME2":"Idensalmi","POP":"21945","AREA":"872180000"},{"COUNTRY_CODE":"FI","NUTS3":"FI1C4","LAU1":"081","LAU2":"142","_CHANGE":"no","NAME1":"Iitti","NAME2":"Iitti","POP":"6910","AREA":"687090000"},{"COUNTRY_CODE":"FI","NUTS3":"FI197","LAU1":"061","LAU2":"143","_CHANGE":"no","NAME1":"Ikaalinen","NAME2":"Ikalis","POP":"7207","AREA":"843400000"},{"COUNTRY_CODE":"FI","NUTS3":"FI194","LAU1":"142","LAU2":"145","_CHANGE":"no","NAME1":"Ilmajoki","NAME2":"Ilmajoki","POP":"12159","AREA":"579680000"},{"COUNTRY_CODE":"FI","NUTS3":"FI1D3","LAU1":"122","LAU2":"146","_CHANGE":"no","NAME1":"Ilomantsi","NAME2":"Ilomants","POP":"5336","AREA":"3172690000"},{"COUNTRY_CODE":"FI","NUTS3":"FI1D7","LAU1":"197","LAU2":"148","_CHANGE":"no","NAME1":"Inari","NAME2":"Enare","POP":"6804","AREA":"17333650000"},{"COUNTRY_CODE":"FI","NUTS3":"FI1B1","LAU1":"014","LAU2":"149","_CHANGE":"no","NAME1":"Inkoo","NAME2":"Ingå","POP":"5541","AREA":"954020000"},{"COUNTRY_CODE":"FI","NUTS3":"FI194","LAU1":"141","LAU2":"151","_CHANGE":"no","NAME1":"Isojoki","NAME2":"Storå","POP":"2123","AREA":"647430000"},{"COUNTRY_CODE":"FI","NUTS3":"FI195","LAU1":"151","LAU2":"152","_CHANGE":"no","NAME1":"Isokyrö","NAME2":"Storkyro","POP":"4785","AREA":"356910000"},{"COUNTRY_CODE":"FI","NUTS3":"FI1C5","LAU1":"093","LAU2":"153","_CHANGE":"no","NAME1":"Imatra","NAME2":"Imatra","POP":"27835","AREA":"191280000"},{"COUNTRY_CODE":"FI","NUTS3":"FI1C2","LAU1":"051","LAU2":"165","_CHANGE":"no","NAME1":"Janakkala","NAME2":"Janakkala","POP":"16853","AREA":"586070000"},{"COUNTRY_CODE":"FI","NUTS3":"FI1D3","LAU1":"122","LAU2":"167","_CHANGE":"no","NAME1":"Joensuu","NAME2":"Joensuu","POP":"75514","AREA":"2751070000"},{"COUNTRY_CODE":"FI","NUTS3":"FI1C2","LAU1":"053","LAU2":"169","_CHANGE":"no","NAME1":"Jokioinen","NAME2":"Jockis","POP":"5425","AREA":"181940000"},{"COUNTRY_CODE":"FI","NUTS3":"FI200","LAU1":"212","LAU2":"170","_CHANGE":"no","NAME1":"Jomala","NAME2":"Jomala","POP":"4648","AREA":"687000000"},{"COUNTRY_CODE":"FI","NUTS3":"FI1D1","LAU1":"105","LAU2":"171","_CHANGE":"no","NAME1":"Joroinen","NAME2":"Jorois","POP":"5110","AREA":"711760000"},{"COUNTRY_CODE":"FI","NUTS3":"FI193","LAU1":"132","LAU2":"172","_CHANGE":"no","NAME1":"Joutsa","NAME2":"Joutsa","POP":"4688","AREA":"1066420000"},{"COUNTRY_CODE":"FI","NUTS3":"FI1D2","LAU1":"113","LAU2":"174","_CHANGE":"no","NAME1":"Juankoski","NAME2":"Juankoski","POP":"4804","AREA":"586260000"},{"COUNTRY_CODE":"FI","NUTS3":"FI1D3","LAU1":"122","LAU2":"176","_CHANGE":"no","NAME1":"Juuka","NAME2":"Juuka","POP":"5034","AREA":"1846560000"},{"COUNTRY_CODE":"FI","NUTS3":"FI197","LAU1":"069","LAU2":"177","_CHANGE":"no","NAME1":"Juupajoki","NAME2":"Juupajoki","POP":"1988","AREA":"274950000"},{"COUNTRY_CODE":"FI","NUTS3":"FI1D1","LAU1":"105","LAU2":"178","_CHANGE":"no","NAME1":"Juva","NAME2":"Juva","POP":"6548","AREA":"1345700000"},{"COUNTRY_CODE":"FI","NUTS3":"FI193","LAU1":"131","LAU2":"179","_CHANGE":"no","NAME1":"Jyväskylä","NAME2":"Jyväskylä","POP":"137368","AREA":"1466350000"},{"COUNTRY_CODE":"FI","NUTS3":"FI196","LAU1":"044","LAU2":"181","_CHANGE":"no","NAME1":"Jämijärvi","NAME2":"Jämijärvi","POP":"1948","AREA":"224330000"},{"COUNTRY_CODE":"FI","NUTS3":"FI193","LAU1":"134","LAU2":"182","_CHANGE":"no","NAME1":"Jämsä","NAME2":"Jämsä","POP":"21542","AREA":"1823770000"},{"COUNTRY_CODE":"FI","NUTS3":"FI1B1","LAU1":"011","LAU2":"186","_CHANGE":"no","NAME1":"Järvenpää","NAME2":"Träskända","POP":"40900","AREA":"39930000"},{"COUNTRY_CODE":"FI","NUTS3":"FI1C1","LAU1":"023","LAU2":"202","_CHANGE":"no","NAME1":"Kaarina","NAME2":"S:t Karins","POP":"32590","AREA":"179580000"},{"COUNTRY_CODE":"FI","NUTS3":"FI1D2","LAU1":"113","LAU2":"204","_CHANGE":"no","NAME1":"Kaavi","NAME2":"Kaavi","POP":"3194","AREA":"789590000"},{"COUNTRY_CODE":"FI","NUTS3":"FI1D4","LAU1":"182","LAU2":"205","_CHANGE":"no","NAME1":"Kajaani","NAME2":"Kajana","POP":"37622","AREA":"2264000000"},{"COUNTRY_CODE":"FI","NUTS3":"FI1D6","LAU1":"177","LAU2":"208","_CHANGE":"no","NAME1":"Kalajoki","NAME2":"Kalajoki","POP":"12621","AREA":"2391300000"},{"COUNTRY_CODE":"FI","NUTS3":"FI197","LAU1":"064","LAU2":"211","_CHANGE":"no","NAME1":"Kangasala","NAME2":"Kangasala","POP":"30607","AREA":"870850000"},{"COUNTRY_CODE":"FI","NUTS3":"FI1D1","LAU1":"101","LAU2":"213","_CHANGE":"no","NAME1":"Kangasniemi","NAME2":"Kangasniemi","POP":"5628","AREA":"1326750000"},{"COUNTRY_CODE":"FI","NUTS3":"FI196","LAU1":"044","LAU2":"214","_CHANGE":"no","NAME1":"Kankaanpää","NAME2":"Kankaanpää","POP":"11769","AREA":"704740000"},{"COUNTRY_CODE":"FI","NUTS3":"FI193","LAU1":"138","LAU2":"216","_CHANGE":"no","NAME1":"Kannonkoski","NAME2":"Kannonkoski","POP":"1462","AREA":"549880000"},{"COUNTRY_CODE":"FI","NUTS3":"FI1D5","LAU1":"162","LAU2":"217","_CHANGE":"no","NAME1":"Kannus","NAME2":"Kannus","POP":"5590","AREA":"470650000"},{"COUNTRY_CODE":"FI","NUTS3":"FI194","LAU1":"141","LAU2":"218","_CHANGE":"no","NAME1":"Karijoki","NAME2":"Bötom","POP":"1369","AREA":"186540000"},{"COUNTRY_CODE":"FI","NUTS3":"FI1B1","LAU1":"011","LAU2":"224","_CHANGE":"no","NAME1":"Karkkila","NAME2":"Högfors","POP":"8969","AREA":"255320000"},{"COUNTRY_CODE":"FI","NUTS3":"FI193","LAU1":"138","LAU2":"226","_CHANGE":"no","NAME1":"Karstula","NAME2":"Karstula","POP":"4268","AREA":"963190000"},{"COUNTRY_CODE":"FI","NUTS3":"FI196","LAU1":"044","LAU2":"230","_CHANGE":"no","NAME1":"Karvia","NAME2":"Karvia","POP":"2475","AREA":"519890000"},{"COUNTRY_CODE":"FI","NUTS3":"FI195","LAU1":"153","LAU2":"231","_CHANGE":"no","NAME1":"Kaskinen","NAME2":"Kaskö","POP":"1285","AREA":"175360000"},{"COUNTRY_CODE":"FI","NUTS3":"FI194","LAU1":"141","LAU2":"232","_CHANGE":"no","NAME1":"Kauhajoki","NAME2":"Kauhajoki","POP":"13875","AREA":"1315550000"},{"COUNTRY_CODE":"FI","NUTS3":"FI194","LAU1":"142","LAU2":"233","_CHANGE":"no","NAME1":"Kauhava","NAME2":"Kauhava","POP":"16784","AREA":"1328080000"},{"COUNTRY_CODE":"FI","NUTS3":"FI1B1","LAU1":"011","LAU2":"235","_CHANGE":"no","NAME1":"Kauniainen","NAME2":"Grankulla","POP":"9486","AREA":"6000000"},{"COUNTRY_CODE":"FI","NUTS3":"FI1D5","LAU1":"161","LAU2":"236","_CHANGE":"no","NAME1":"Kaustinen","NAME2":"Kaustby","POP":"4305","AREA":"361120000"},{"COUNTRY_CODE":"FI","NUTS3":"FI1D2","LAU1":"111","LAU2":"239","_CHANGE":"no","NAME1":"Keitele","NAME2":"Keitele","POP":"2379","AREA":"578320000"},{"COUNTRY_CODE":"FI","NUTS3":"FI1D7","LAU1":"192","LAU2":"240","_CHANGE":"no","NAME1":"Kemi","NAME2":"Kemi","POP":"21758","AREA":"747280000"},{"COUNTRY_CODE":"FI","NUTS3":"FI1D7","LAU1":"192","LAU2":"241","_CHANGE":"no","NAME1":"Keminmaa","NAME2":"Keminmaa","POP":"8388","AREA":"647230000"},{"COUNTRY_CODE":"FI","NUTS3":"FI1D6","LAU1":"171","LAU2":"244","_CHANGE":"no","NAME1":"Kempele","NAME2":"Kempele","POP":"17066","AREA":"110350000"},{"COUNTRY_CODE":"FI","NUTS3":"FI1B1","LAU1":"011","LAU2":"245","_CHANGE":"no","NAME1":"Kerava","NAME2":"Kervo","POP":"35293","AREA":"30790000"},{"COUNTRY_CODE":"FI","NUTS3":"FI193","LAU1":"133","LAU2":"249","_CHANGE":"no","NAME1":"Keuruu","NAME2":"Keuruu","POP":"10117","AREA":"1430560000"},{"COUNTRY_CODE":"FI","NUTS3":"FI197","LAU1":"061","LAU2":"250","_CHANGE":"no","NAME1":"Kihniö","NAME2":"Kihniö","POP":"2038","AREA":"390500000"},{"COUNTRY_CODE":"FI","NUTS3":"FI193","LAU1":"138","LAU2":"256","_CHANGE":"no","NAME1":"Kinnula","NAME2":"Kinnula","POP":"1745","AREA":"495720000"},{"COUNTRY_CODE":"FI","NUTS3":"FI1B1","LAU1":"011","LAU2":"257","_CHANGE":"no","NAME1":"Kirkkonummi","NAME2":"Kyrkslätt","POP":"38649","AREA":"1017010000"},{"COUNTRY_CODE":"FI","NUTS3":"FI1D3","LAU1":"124","LAU2":"260","_CHANGE":"no","NAME1":"Kitee","NAME2":"Kitee","POP":"10832","AREA":"1724410000"},{"COUNTRY_CODE":"FI","NUTS3":"FI1D7","LAU1":"196","LAU2":"261","_CHANGE":"no","NAME1":"Kittilä","NAME2":"Kittilä","POP":"6416","AREA":"8262930000"},{"COUNTRY_CODE":"FI","NUTS3":"FI1D2","LAU1":"111","LAU2":"263","_CHANGE":"no","NAME1":"Kiuruvesi","NAME2":"Kiuruvesi","POP":"8600","AREA":"1422900000"},{"COUNTRY_CODE":"FI","NUTS3":"FI193","LAU1":"138","LAU2":"265","_CHANGE":"no","NAME1":"Kivijärvi","NAME2":"Kivijärvi","POP":"1200","AREA":"599870000"},{"COUNTRY_CODE":"FI","NUTS3":"FI196","LAU1":"043","LAU2":"271","_CHANGE":"no","NAME1":"Kokemäki","NAME2":"Kumo","POP":"7591","AREA":"531270000"},{"COUNTRY_CODE":"FI","NUTS3":"FI1D5","LAU1":"162","LAU2":"272","_CHANGE":"no","NAME1":"Kokkola","NAME2":"Karleby","POP":"47570","AREA":"2730800000"},{"COUNTRY_CODE":"FI","NUTS3":"FI1D7","LAU1":"196","LAU2":"273","_CHANGE":"no","NAME1":"Kolari","NAME2":"Kolari","POP":"3848","AREA":"2617770000"},{"COUNTRY_CODE":"FI","NUTS3":"FI193","LAU1":"135","LAU2":"275","_CHANGE":"no","NAME1":"Konnevesi","NAME2":"Konnevesi","POP":"2757","AREA":"680850000"},{"COUNTRY_CODE":"FI","NUTS3":"FI1D3","LAU1":"122","LAU2":"276","_CHANGE":"no","NAME1":"Kontiolahti","NAME2":"Kontiolahti","POP":"14827","AREA":"1029820000"},{"COUNTRY_CODE":"FI","NUTS3":"FI195","LAU1":"152","LAU2":"280","_CHANGE":"no","NAME1":"Korsnäs","NAME2":"Korsnäs","POP":"2201","AREA":"1424700000"},{"COUNTRY_CODE":"FI","NUTS3":"FI1C1","LAU1":"025","LAU2":"284","_CHANGE":"no","NAME1":"Koski Tl","NAME2":"Koski Tl","POP":"2399","AREA":"192420000"},{"COUNTRY_CODE":"FI","NUTS3":"FI1C4","LAU1":"082","LAU2":"285","_CHANGE":"no","NAME1":"Kotka","NAME2":"Kotka","POP":"54319","AREA":"949780000"},{"COUNTRY_CODE":"FI","NUTS3":"FI1C4","LAU1":"081","LAU2":"286","_CHANGE":"no","NAME1":"Kouvola","NAME2":"Kouvola","POP":"85855","AREA":"2883290000"},{"COUNTRY_CODE":"FI","NUTS3":"FI195","LAU1":"153","LAU2":"287","_CHANGE":"no","NAME1":"Kristiinankaupunki","NAME2":"Kristinestad","POP":"6793","AREA":"1678980000"},{"COUNTRY_CODE":"FI","NUTS3":"FI195","LAU1":"154","LAU2":"288","_CHANGE":"no","NAME1":"Kruunupyy","NAME2":"Kronoby","POP":"6682","AREA":"752650000"},{"COUNTRY_CODE":"FI","NUTS3":"FI1D4","LAU1":"181","LAU2":"290","_CHANGE":"no","NAME1":"Kuhmo","NAME2":"Kuhmo","POP":"8806","AREA":"5456780000"},{"COUNTRY_CODE":"FI","NUTS3":"FI193","LAU1":"134","LAU2":"291","_CHANGE":"no","NAME1":"Kuhmoinen","NAME2":"Kuhmoinen","POP":"2334","AREA":"936680000"},{"COUNTRY_CODE":"FI","NUTS3":"FI200","LAU1":"213","LAU2":"295","_CHANGE":"no","NAME1":"Kumlinge","NAME2":"Kumlinge","POP":"317","AREA":"865880000"},{"COUNTRY_CODE":"FI","NUTS3":"FI1D2","LAU1":"112","LAU2":"297","_CHANGE":"no","NAME1":"Kuopio","NAME2":"Kuopio","POP":"112117","AREA":"3740100000"},{"COUNTRY_CODE":"FI","NUTS3":"FI194","LAU1":"144","LAU2":"300","_CHANGE":"no","NAME1":"Kuortane","NAME2":"Kuortane","POP":"3715","AREA":"484880000"},{"COUNTRY_CODE":"FI","NUTS3":"FI194","LAU1":"142","LAU2":"301","_CHANGE":"1/1/16","NAME1":"Kurikka","NAME2":"Kurikka","POP":"21734","AREA":"1743860000"},{"COUNTRY_CODE":"FI","NUTS3":"FI1C1","LAU1":"024","LAU2":"304","_CHANGE":"no","NAME1":"Kustavi","NAME2":"Gustavs","POP":"895","AREA":"770100000"},{"COUNTRY_CODE":"FI","NUTS3":"FI1D6","LAU1":"178","LAU2":"305","_CHANGE":"no","NAME1":"Kuusamo","NAME2":"Kuusamo","POP":"15688","AREA":"5808920000"},{"COUNTRY_CODE":"FI","NUTS3":"FI1D3","LAU1":"122","LAU2":"309","_CHANGE":"no","NAME1":"Outokumpu","NAME2":"Outokumpu","POP":"7139","AREA":"584050000"},{"COUNTRY_CODE":"FI","NUTS3":"FI193","LAU1":"138","LAU2":"312","_CHANGE":"no","NAME1":"Kyyjärvi","NAME2":"Kyyjärvi","POP":"1379","AREA":"469620000"},{"COUNTRY_CODE":"FI","NUTS3":"FI1C3","LAU1":"071","LAU2":"316","_CHANGE":"no","NAME1":"Kärkölä","NAME2":"Kärkölä","POP":"4604","AREA":"259300000"},{"COUNTRY_CODE":"FI","NUTS3":"FI1D6","LAU1":"176","LAU2":"317","_CHANGE":"no","NAME1":"Kärsämäki","NAME2":"Kärsämäki","POP":"2658","AREA":"700900000"},{"COUNTRY_CODE":"FI","NUTS3":"FI200","LAU1":"213","LAU2":"318","_CHANGE":"no","NAME1":"Kökar","NAME2":"Kökar","POP":"250","AREA":"2165020000"},{"COUNTRY_CODE":"FI","NUTS3":"FI1D7","LAU1":"194","LAU2":"320","_CHANGE":"no","NAME1":"Kemijärvi","NAME2":"Kemijärvi","POP":"7766","AREA":"3930910000"},{"COUNTRY_CODE":"FI","NUTS3":"FI1C1","LAU1":"021","LAU2":"322","_CHANGE":"no","NAME1":"Kemiönsaari","NAME2":"Kimitoön","POP":"6909","AREA":"2801210000"},{"COUNTRY_CODE":"FI","NUTS3":"FI1C3","LAU1":"071","LAU2":"398","_CHANGE":"no","NAME1":"Lahti","NAME2":"Lahtis","POP":"118743","AREA":"517630000"},{"COUNTRY_CODE":"FI","NUTS3":"FI195","LAU1":"151","LAU2":"399","_CHANGE":"no","NAME1":"Laihia","NAME2":"Laihela","POP":"8090","AREA":"508440000"},{"COUNTRY_CODE":"FI","NUTS3":"FI1C1","LAU1":"024","LAU2":"400","_CHANGE":"no","NAME1":"Laitila","NAME2":"Laitila","POP":"8520","AREA":"545330000"},{"COUNTRY_CODE":"FI","NUTS3":"FI1D2","LAU1":"111","LAU2":"402","_CHANGE":"no","NAME1":"Lapinlahti","NAME2":"Lapinlahti","POP":"9982","AREA":"1245140000"},{"COUNTRY_CODE":"FI","NUTS3":"FI194","LAU1":"146","LAU2":"403","_CHANGE":"no","NAME1":"Lappajärvi","NAME2":"Lappajärvi","POP":"3215","AREA":"522980000"},{"COUNTRY_CODE":"FI","NUTS3":"FI1C5","LAU1":"091","LAU2":"405","_CHANGE":"no","NAME1":"Lappeenranta","NAME2":"Villmanstrand","POP":"72875","AREA":"1723550000"},{"COUNTRY_CODE":"FI","NUTS3":"FI1B1","LAU1":"016","LAU2":"407","_CHANGE":"no","NAME1":"Lapinjärvi","NAME2":"Lappträsk","POP":"2774","AREA":"339310000"},{"COUNTRY_CODE":"FI","NUTS3":"FI194","LAU1":"142","LAU2":"408","_CHANGE":"no","NAME1":"Lapua","NAME2":"Lappo","POP":"14609","AREA":"751800000"},{"COUNTRY_CODE":"FI","NUTS3":"FI193","LAU1":"131","LAU2":"410","_CHANGE":"no","NAME1":"Laukaa","NAME2":"Laukaa","POP":"18865","AREA":"825590000"},{"COUNTRY_CODE":"FI","NUTS3":"FI1C5","LAU1":"091","LAU2":"416","_CHANGE":"no","NAME1":"Lemi","NAME2":"Lemi","POP":"3073","AREA":"262480000"},{"COUNTRY_CODE":"FI","NUTS3":"FI200","LAU1":"212","LAU2":"417","_CHANGE":"no","NAME1":"Lemland","NAME2":"Lemland","POP":"1991","AREA":"965300000"},{"COUNTRY_CODE":"FI","NUTS3":"FI197","LAU1":"064","LAU2":"418","_CHANGE":"no","NAME1":"Lempäälä","NAME2":"Lempäälä","POP":"22536","AREA":"307060000"},{"COUNTRY_CODE":"FI","NUTS3":"FI1D2","LAU1":"114","LAU2":"420","_CHANGE":"no","NAME1":"Leppävirta","NAME2":"Leppävirta","POP":"9953","AREA":"1519650000"},{"COUNTRY_CODE":"FI","NUTS3":"FI1D5","LAU1":"161","LAU2":"421","_CHANGE":"no","NAME1":"Lestijärvi","NAME2":"Lestijärvi","POP":"798","AREA":"559060000"},{"COUNTRY_CODE":"FI","NUTS3":"FI1D3","LAU1":"125","LAU2":"422","_CHANGE":"no","NAME1":"Lieksa","NAME2":"Lieksa","POP":"11772","AREA":"4067600000"},{"COUNTRY_CODE":"FI","NUTS3":"FI1C1","LAU1":"023","LAU2":"423","_CHANGE":"no","NAME1":"Lieto","NAME2":"Lundo","POP":"19263","AREA":"302560000"},{"COUNTRY_CODE":"FI","NUTS3":"FI1D6","LAU1":"171","LAU2":"425","_CHANGE":"no","NAME1":"Liminka","NAME2":"Limingo","POP":"9937","AREA":"651710000"},{"COUNTRY_CODE":"FI","NUTS3":"FI1D3","LAU1":"122","LAU2":"426","_CHANGE":"no","NAME1":"Liperi","NAME2":"Liperi","POP":"12338","AREA":"1161230000"},{"COUNTRY_CODE":"FI","NUTS3":"FI1C1","LAU1":"025","LAU2":"430","_CHANGE":"no","NAME1":"Loimaa","NAME2":"Loimaa","POP":"16467","AREA":"851930000"},{"COUNTRY_CODE":"FI","NUTS3":"FI1C2","LAU1":"052","LAU2":"433","_CHANGE":"no","NAME1":"Loppi","NAME2":"Loppi","POP":"8175","AREA":"655970000"},{"COUNTRY_CODE":"FI","NUTS3":"FI1B1","LAU1":"016","LAU2":"434","_CHANGE":"no","NAME1":"Loviisa","NAME2":"Lovisa","POP":"15311","AREA":"1751520000"},{"COUNTRY_CODE":"FI","NUTS3":"FI193","LAU1":"132","LAU2":"435","_CHANGE":"no","NAME1":"Luhanka","NAME2":"Luhanka","POP":"761","AREA":"313250000"},{"COUNTRY_CODE":"FI","NUTS3":"FI1D6","LAU1":"171","LAU2":"436","_CHANGE":"no","NAME1":"Lumijoki","NAME2":"Lumijoki","POP":"2076","AREA":"290290000"},{"COUNTRY_CODE":"FI","NUTS3":"FI200","LAU1":"212","LAU2":"438","_CHANGE":"no","NAME1":"Lumparland","NAME2":"Lumparland","POP":"398","AREA":"87040000"},{"COUNTRY_CODE":"FI","NUTS3":"FI195","LAU1":"154","LAU2":"440","_CHANGE":"no","NAME1":"Luoto","NAME2":"Larsmo","POP":"5147","AREA":"853280000"},{"COUNTRY_CODE":"FI","NUTS3":"FI1C5","LAU1":"091","LAU2":"441","_CHANGE":"no","NAME1":"Luumäki","NAME2":"Luumäki","POP":"4860","AREA":"859840000"},{"COUNTRY_CODE":"FI","NUTS3":"FI196","LAU1":"043","LAU2":"442","_CHANGE":"no","NAME1":"Luvia","NAME2":"Luvia","POP":"3349","AREA":"861200000"},{"COUNTRY_CODE":"FI","NUTS3":"FI1B1","LAU1":"011","LAU2":"444","_CHANGE":"no","NAME1":"Lohja","NAME2":"Lojo","POP":"47353","AREA":"1109730000"},{"COUNTRY_CODE":"FI","NUTS3":"FI1C1","LAU1":"021","LAU2":"445","_CHANGE":"no","NAME1":"Parainen","NAME2":"Pargas","POP":"15457","AREA":"5548090000"},{"COUNTRY_CODE":"FI","NUTS3":"FI195","LAU1":"152","LAU2":"475","_CHANGE":"no","NAME1":"Maalahti","NAME2":"Malax","POP":"5545","AREA":"1954940000"},{"COUNTRY_CODE":"FI","NUTS3":"FI200","LAU1":"211","LAU2":"478","_CHANGE":"no","NAME1":"Maarianhamina - Mariehamn","NAME2":"Mariehamn","POP":"11461","AREA":"20750000"},{"COUNTRY_CODE":"FI","NUTS3":"FI1C1","LAU1":"025","LAU2":"480","_CHANGE":"no","NAME1":"Marttila","NAME2":"Marttila","POP":"2028","AREA":"195990000"},{"COUNTRY_CODE":"FI","NUTS3":"FI1C1","LAU1":"023","LAU2":"481","_CHANGE":"no","NAME1":"Masku","NAME2":"Masku","POP":"9706","AREA":"204020000"},{"COUNTRY_CODE":"FI","NUTS3":"FI1D6","LAU1":"177","LAU2":"483","_CHANGE":"no","NAME1":"Merijärvi","NAME2":"Merijärvi","POP":"1134","AREA":"231630000"},{"COUNTRY_CODE":"FI","NUTS3":"FI196","LAU1":"043","LAU2":"484","_CHANGE":"no","NAME1":"Merikarvia","NAME2":"Sastmola","POP":"3185","AREA":"1246220000"},{"COUNTRY_CODE":"FI","NUTS3":"FI1C4","LAU1":"082","LAU2":"489","_CHANGE":"no","NAME1":"Miehikkälä","NAME2":"Miehikkälä","POP":"2085","AREA":"440350000"},{"COUNTRY_CODE":"FI","NUTS3":"FI1D1","LAU1":"101","LAU2":"491","_CHANGE":"no","NAME1":"Mikkeli","NAME2":"S:t Michel","POP":"54665","AREA":"3229570000"},{"COUNTRY_CODE":"FI","NUTS3":"FI1D6","LAU1":"171","LAU2":"494","_CHANGE":"no","NAME1":"Muhos","NAME2":"Muhos","POP":"9063","AREA":"797270000"},{"COUNTRY_CODE":"FI","NUTS3":"FI193","LAU1":"133","LAU2":"495","_CHANGE":"no","NAME1":"Multia","NAME2":"Multia","POP":"1710","AREA":"765620000"},{"COUNTRY_CODE":"FI","NUTS3":"FI1D7","LAU1":"196","LAU2":"498","_CHANGE":"no","NAME1":"Muonio","NAME2":"Muonio","POP":"2358","AREA":"2037790000"},{"COUNTRY_CODE":"FI","NUTS3":"FI195","LAU1":"152","LAU2":"499","_CHANGE":"no","NAME1":"Mustasaari","NAME2":"Korsholm","POP":"19302","AREA":"3178610000"},{"COUNTRY_CODE":"FI","NUTS3":"FI193","LAU1":"131","LAU2":"500","_CHANGE":"no","NAME1":"Muurame","NAME2":"Muurame","POP":"9791","AREA":"194050000"},{"COUNTRY_CODE":"FI","NUTS3":"FI1C1","LAU1":"023","LAU2":"503","_CHANGE":"no","NAME1":"Mynämäki","NAME2":"Mynämäki","POP":"7859","AREA":"536090000"},{"COUNTRY_CODE":"FI","NUTS3":"FI1B1","LAU1":"015","LAU2":"504","_CHANGE":"no","NAME1":"Myrskylä","NAME2":"Mörskom","POP":"1969","AREA":"206350000"},{"COUNTRY_CODE":"FI","NUTS3":"FI1B1","LAU1":"011","LAU2":"505","_CHANGE":"no","NAME1":"Mäntsälä","NAME2":"Mäntsälä","POP":"20685","AREA":"596110000"},{"COUNTRY_CODE":"FI","NUTS3":"FI1D1","LAU1":"101","LAU2":"507","_CHANGE":"no","NAME1":"Mäntyharju","NAME2":"Mäntyharju","POP":"6159","AREA":"1210980000"},{"COUNTRY_CODE":"FI","NUTS3":"FI197","LAU1":"069","LAU2":"508","_CHANGE":"no","NAME1":"Mänttä-Vilppula","NAME2":"Mänttä-Vilppula","POP":"10604","AREA":"657230000"},{"COUNTRY_CODE":"FI","NUTS3":"FI1C1","LAU1":"023","LAU2":"529","_CHANGE":"no","NAME1":"Naantali","NAME2":"Nådendal","POP":"18961","AREA":"687970000"},{"COUNTRY_CODE":"FI","NUTS3":"FI196","LAU1":"043","LAU2":"531","_CHANGE":"no","NAME1":"Nakkila","NAME2":"Nakkila","POP":"5651","AREA":"184880000"},{"COUNTRY_CODE":"FI","NUTS3":"FI1D6","LAU1":"176","LAU2":"535","_CHANGE":"no","NAME1":"Nivala","NAME2":"Nivala","POP":"10876","AREA":"536880000"},{"COUNTRY_CODE":"FI","NUTS3":"FI197","LAU1":"064","LAU2":"536","_CHANGE":"no","NAME1":"Nokia","NAME2":"Nokia","POP":"33162","AREA":"347750000"},{"COUNTRY_CODE":"FI","NUTS3":"FI1C1","LAU1":"023","LAU2":"538","_CHANGE":"no","NAME1":"Nousiainen","NAME2":"Nousis","POP":"4859","AREA":"199550000"},{"COUNTRY_CODE":"FI","NUTS3":"FI1D3","LAU1":"125","LAU2":"541","_CHANGE":"no","NAME1":"Nurmes","NAME2":"Nurmes","POP":"7996","AREA":"1854800000"},{"COUNTRY_CODE":"FI","NUTS3":"FI1B1","LAU1":"011","LAU2":"543","_CHANGE":"no","NAME1":"Nurmijärvi","NAME2":"Nurmijärvi","POP":"41897","AREA":"367260000"},{"COUNTRY_CODE":"FI","NUTS3":"FI195","LAU1":"153","LAU2":"545","_CHANGE":"no","NAME1":"Närpiö","NAME2":"Närpes","POP":"9387","AREA":"2334140000"},{"COUNTRY_CODE":"FI","NUTS3":"FI1C3","LAU1":"071","LAU2":"560","_CHANGE":"no","NAME1":"Orimattila","NAME2":"Orimattila","POP":"16326","AREA":"814010000"},{"COUNTRY_CODE":"FI","NUTS3":"FI1C1","LAU1":"025","LAU2":"561","_CHANGE":"no","NAME1":"Oripää","NAME2":"Oripää","POP":"1377","AREA":"117720000"},{"COUNTRY_CODE":"FI","NUTS3":"FI197","LAU1":"064","LAU2":"562","_CHANGE":"no","NAME1":"Orivesi","NAME2":"Orivesi","POP":"9408","AREA":"960080000"},{"COUNTRY_CODE":"FI","NUTS3":"FI1D6","LAU1":"177","LAU2":"563","_CHANGE":"no","NAME1":"Oulainen","NAME2":"Oulainen","POP":"7610","AREA":"597530000"},{"COUNTRY_CODE":"FI","NUTS3":"FI1D6","LAU1":"171","LAU2":"564","_CHANGE":"no","NAME1":"Oulu","NAME2":"Uleåborg","POP":"198525","AREA":"3880620000"},{"COUNTRY_CODE":"FI","NUTS3":"FI1C3","LAU1":"071","LAU2":"576","_CHANGE":"no","NAME1":"Padasjoki","NAME2":"Padasjoki","POP":"3143","AREA":"729860000"},{"COUNTRY_CODE":"FI","NUTS3":"FI1C1","LAU1":"023","LAU2":"577","_CHANGE":"no","NAME1":"Paimio","NAME2":"Pemar","POP":"10620","AREA":"242260000"},{"COUNTRY_CODE":"FI","NUTS3":"FI1D4","LAU1":"182","LAU2":"578","_CHANGE":"no","NAME1":"Paltamo","NAME2":"Paltamo","POP":"3488","AREA":"1139120000"},{"COUNTRY_CODE":"FI","NUTS3":"FI1C5","LAU1":"093","LAU2":"580","_CHANGE":"no","NAME1":"Parikkala","NAME2":"Parikkala","POP":"5235","AREA":"760720000"},{"COUNTRY_CODE":"FI","NUTS3":"FI197","LAU1":"061","LAU2":"581","_CHANGE":"no","NAME1":"Parkano","NAME2":"Parkano","POP":"6766","AREA":"909670000"},{"COUNTRY_CODE":"FI","NUTS3":"FI1D7","LAU1":"194","LAU2":"583","_CHANGE":"no","NAME1":"Pelkosenniemi","NAME2":"Pelkosenniemi","POP":"958","AREA":"1881570000"},{"COUNTRY_CODE":"FI","NUTS3":"FI1D5","LAU1":"161","LAU2":"584","_CHANGE":"no","NAME1":"Perho","NAME2":"Perho","POP":"2931","AREA":"775190000"},{"COUNTRY_CODE":"FI","NUTS3":"FI1D1","LAU1":"101","LAU2":"588","_CHANGE":"no","NAME1":"Pertunmaa","NAME2":"Pertunmaa","POP":"1817","AREA":"454190000"},{"COUNTRY_CODE":"FI","NUTS3":"FI193","LAU1":"131","LAU2":"592","_CHANGE":"no","NAME1":"Petäjävesi","NAME2":"Petäjävesi","POP":"4008","AREA":"495420000"},{"COUNTRY_CODE":"FI","NUTS3":"FI1D1","LAU1":"105","LAU2":"593","_CHANGE":"no","NAME1":"Pieksämäki","NAME2":"Pieksämäki","POP":"18801","AREA":"1836220000"},{"COUNTRY_CODE":"FI","NUTS3":"FI1D2","LAU1":"111","LAU2":"595","_CHANGE":"no","NAME1":"Pielavesi","NAME2":"Pielavesi","POP":"4740","AREA":"1406510000"},{"COUNTRY_CODE":"FI","NUTS3":"FI195","LAU1":"154","LAU2":"598","_CHANGE":"no","NAME1":"Pietarsaari","NAME2":"Jakobstad","POP":"19436","AREA":"396350000"},{"COUNTRY_CODE":"FI","NUTS3":"FI195","LAU1":"154","LAU2":"599","_CHANGE":"no","NAME1":"Pedersören kunta","NAME2":"Pedersöre","POP":"11129","AREA":"826050000"},{"COUNTRY_CODE":"FI","NUTS3":"FI193","LAU1":"138","LAU2":"601","_CHANGE":"no","NAME1":"Pihtipudas","NAME2":"Pihtipudas","POP":"4221","AREA":"1247450000"},{"COUNTRY_CODE":"FI","NUTS3":"FI197","LAU1":"064","LAU2":"604","_CHANGE":"no","NAME1":"Pirkkala","NAME2":"Birkala","POP":"18913","AREA":"104040000"},{"COUNTRY_CODE":"FI","NUTS3":"FI1D3","LAU1":"122","LAU2":"607","_CHANGE":"no","NAME1":"Polvijärvi","NAME2":"Polvijärvi","POP":"4556","AREA":"958330000"},{"COUNTRY_CODE":"FI","NUTS3":"FI196","LAU1":"043","LAU2":"608","_CHANGE":"no","NAME1":"Pomarkku","NAME2":"Påmark","POP":"2240","AREA":"332040000"},{"COUNTRY_CODE":"FI","NUTS3":"FI196","LAU1":"043","LAU2":"609","_CHANGE":"no","NAME1":"Pori","NAME2":"Björneborg","POP":"85363","AREA":"2061980000"},{"COUNTRY_CODE":"FI","NUTS3":"FI1B1","LAU1":"011","LAU2":"611","_CHANGE":"no","NAME1":"Pornainen","NAME2":"Borgnäs","POP":"5125","AREA":"150090000"},{"COUNTRY_CODE":"FI","NUTS3":"FI1D7","LAU1":"194","LAU2":"614","_CHANGE":"no","NAME1":"Posio","NAME2":"Posio","POP":"3477","AREA":"3544900000"},{"COUNTRY_CODE":"FI","NUTS3":"FI1D6","LAU1":"173","LAU2":"615","_CHANGE":"no","NAME1":"Pudasjärvi","NAME2":"Pudasjärvi","POP":"8257","AREA":"5867250000"},{"COUNTRY_CODE":"FI","NUTS3":"FI1B1","LAU1":"015","LAU2":"616","_CHANGE":"no","NAME1":"Pukkila","NAME2":"Pukkila","POP":"1971","AREA":"145940000"},{"COUNTRY_CODE":"FI","NUTS3":"FI197","LAU1":"068","LAU2":"619","_CHANGE":"no","NAME1":"Punkalaidun","NAME2":"Punkalaidun","POP":"3049","AREA":"364020000"},{"COUNTRY_CODE":"FI","NUTS3":"FI1D4","LAU1":"181","LAU2":"620","_CHANGE":"no","NAME1":"Puolanka","NAME2":"Puolanka","POP":"2776","AREA":"2598680000"},{"COUNTRY_CODE":"FI","NUTS3":"FI1D1","LAU1":"101","LAU2":"623","_CHANGE":"no","NAME1":"Puumala","NAME2":"Puumala","POP":"2260","AREA":"1237750000"},{"COUNTRY_CODE":"FI","NUTS3":"FI1C4","LAU1":"082","LAU2":"624","_CHANGE":"no","NAME1":"Pyhtää","NAME2":"Pyttis","POP":"5321","AREA":"780960000"},{"COUNTRY_CODE":"FI","NUTS3":"FI1D6","LAU1":"174","LAU2":"625","_CHANGE":"no","NAME1":"Pyhäjoki","NAME2":"Pyhäjoki","POP":"3211","AREA":"1365090000"},{"COUNTRY_CODE":"FI","NUTS3":"FI1D6","LAU1":"176","LAU2":"626","_CHANGE":"no","NAME1":"Pyhäjärvi","NAME2":"Pyhäjärvi","POP":"5505","AREA":"1459470000"},{"COUNTRY_CODE":"FI","NUTS3":"FI1D6","LAU1":"175","LAU2":"630","_CHANGE":"no","NAME1":"Pyhäntä","NAME2":"Pyhäntä","POP":"1587","AREA":"847480000"},{"COUNTRY_CODE":"FI","NUTS3":"FI1C1","LAU1":"024","LAU2":"631","_CHANGE":"no","NAME1":"Pyhäranta","NAME2":"Pyhäranta","POP":"2136","AREA":"291740000"},{"COUNTRY_CODE":"FI","NUTS3":"FI197","LAU1":"064","LAU2":"635","_CHANGE":"no","NAME1":"Pälkäne","NAME2":"Pälkäne","POP":"6676","AREA":"738150000"},{"COUNTRY_CODE":"FI","NUTS3":"FI1C1","LAU1":"025","LAU2":"636","_CHANGE":"no","NAME1":"Pöytyä","NAME2":"Pöytyä","POP":"8562","AREA":"773690000"},{"COUNTRY_CODE":"FI","NUTS3":"FI1B1","LAU1":"015","LAU2":"638","_CHANGE":"no","NAME1":"Porvoo","NAME2":"Borgå","POP":"49928","AREA":"2139810000"},{"COUNTRY_CODE":"FI","NUTS3":"FI1D6","LAU1":"174","LAU2":"678","_CHANGE":"no","NAME1":"Raahe","NAME2":"Brahestad","POP":"25165","AREA":"1888930000"},{"COUNTRY_CODE":"FI","NUTS3":"FI1C1","LAU1":"023","LAU2":"680","_CHANGE":"no","NAME1":"Raisio","NAME2":"Reso","POP":"24290","AREA":"50060000"},{"COUNTRY_CODE":"FI","NUTS3":"FI1D1","LAU1":"103","LAU2":"681","_CHANGE":"no","NAME1":"Rantasalmi","NAME2":"Rantasalmi","POP":"3733","AREA":"925190000"},{"COUNTRY_CODE":"FI","NUTS3":"FI1D7","LAU1":"191","LAU2":"683","_CHANGE":"no","NAME1":"Ranua","NAME2":"Ranua","POP":"4020","AREA":"3694800000"},{"COUNTRY_CODE":"FI","NUTS3":"FI196","LAU1":"041","LAU2":"684","_CHANGE":"no","NAME1":"Rauma","NAME2":"Raumo","POP":"39809","AREA":"1110130000"},{"COUNTRY_CODE":"FI","NUTS3":"FI1D2","LAU1":"115","LAU2":"686","_CHANGE":"no","NAME1":"Rautalampi","NAME2":"Rautalampi","POP":"3303","AREA":"761980000"},{"COUNTRY_CODE":"FI","NUTS3":"FI1D2","LAU1":"113","LAU2":"687","_CHANGE":"no","NAME1":"Rautavaara","NAME2":"Rautavaara","POP":"1737","AREA":"1235260000"},{"COUNTRY_CODE":"FI","NUTS3":"FI1C5","LAU1":"093","LAU2":"689","_CHANGE":"no","NAME1":"Rautjärvi","NAME2":"Rautjärvi","POP":"3537","AREA":"401890000"},{"COUNTRY_CODE":"FI","NUTS3":"FI1D6","LAU1":"176","LAU2":"691","_CHANGE":"no","NAME1":"Reisjärvi","NAME2":"Reisjärvi","POP":"2894","AREA":"503180000"},{"COUNTRY_CODE":"FI","NUTS3":"FI1C2","LAU1":"052","LAU2":"694","_CHANGE":"no","NAME1":"Riihimäki","NAME2":"Riihimäki","POP":"29269","AREA":"125560000"},{"COUNTRY_CODE":"FI","NUTS3":"FI1D4","LAU1":"182","LAU2":"697","_CHANGE":"no","NAME1":"Ristijärvi","NAME2":"Ristijärvi","POP":"1351","AREA":"897930000"},{"COUNTRY_CODE":"FI","NUTS3":"FI1D7","LAU1":"191","LAU2":"698","_CHANGE":"no","NAME1":"Rovaniemi","NAME2":"Rovaniemi","POP":"61838","AREA":"8016730000"},{"COUNTRY_CODE":"FI","NUTS3":"FI1C5","LAU1":"093","LAU2":"700","_CHANGE":"no","NAME1":"Ruokolahti","NAME2":"Ruokolahti","POP":"5312","AREA":"1219850000"},{"COUNTRY_CODE":"FI","NUTS3":"FI197","LAU1":"069","LAU2":"702","_CHANGE":"no","NAME1":"Ruovesi","NAME2":"Ruovesi","POP":"4623","AREA":"950150000"},{"COUNTRY_CODE":"FI","NUTS3":"FI1C1","LAU1":"023","LAU2":"704","_CHANGE":"no","NAME1":"Rusko","NAME2":"Rusko","POP":"6110","AREA":"127900000"},{"COUNTRY_CODE":"FI","NUTS3":"FI1D3","LAU1":"124","LAU2":"707","_CHANGE":"no","NAME1":"Rääkkylä","NAME2":"Rääkkylä","POP":"2349","AREA":"699680000"},{"COUNTRY_CODE":"FI","NUTS3":"FI1B1","LAU1":"014","LAU2":"710","_CHANGE":"no","NAME1":"Raasepori","NAME2":"Raseborg","POP":"28405","AREA":"2354260000"},{"COUNTRY_CODE":"FI","NUTS3":"FI193","LAU1":"138","LAU2":"729","_CHANGE":"no","NAME1":"Saarijärvi","NAME2":"Saarijärvi","POP":"9915","AREA":"1422720000"},{"COUNTRY_CODE":"FI","NUTS3":"FI1D7","LAU1":"194","LAU2":"732","_CHANGE":"no","NAME1":"Salla","NAME2":"Salla","POP":"3727","AREA":"5873080000"},{"COUNTRY_CODE":"FI","NUTS3":"FI1C1","LAU1":"022","LAU2":"734","_CHANGE":"no","NAME1":"Salo","NAME2":"Salo","POP":"53890","AREA":"2168310000"},{"COUNTRY_CODE":"FI","NUTS3":"FI200","LAU1":"212","LAU2":"736","_CHANGE":"no","NAME1":"Saltvik","NAME2":"Saltvik","POP":"1829","AREA":"1166540000"},{"COUNTRY_CODE":"FI","NUTS3":"FI1C1","LAU1":"023","LAU2":"738","_CHANGE":"no","NAME1":"Sauvo","NAME2":"Sagu","POP":"3019","AREA":"299490000"},{"COUNTRY_CODE":"FI","NUTS3":"FI1C5","LAU1":"091","LAU2":"739","_CHANGE":"no","NAME1":"Savitaipale","NAME2":"Savitaipale","POP":"3613","AREA":"690560000"},{"COUNTRY_CODE":"FI","NUTS3":"FI1D1","LAU1":"103","LAU2":"740","_CHANGE":"no","NAME1":"Savonlinna","NAME2":"Nyslott","POP":"35523","AREA":"3597710000"},{"COUNTRY_CODE":"FI","NUTS3":"FI1D7","LAU1":"194","LAU2":"742","_CHANGE":"no","NAME1":"Savukoski","NAME2":"Savukoski","POP":"1061","AREA":"6495950000"},{"COUNTRY_CODE":"FI","NUTS3":"FI194","LAU1":"142","LAU2":"743","_CHANGE":"no","NAME1":"Seinäjoki","NAME2":"Seinäjoki","POP":"61530","AREA":"1469250000"},{"COUNTRY_CODE":"FI","NUTS3":"FI1D6","LAU1":"177","LAU2":"746","_CHANGE":"no","NAME1":"Sievi","NAME2":"Sievi","POP":"5124","AREA":"800790000"},{"COUNTRY_CODE":"FI","NUTS3":"FI196","LAU1":"044","LAU2":"747","_CHANGE":"no","NAME1":"Siikainen","NAME2":"Siikainen","POP":"1527","AREA":"491340000"},{"COUNTRY_CODE":"FI","NUTS3":"FI1D6","LAU1":"174","LAU2":"748","_CHANGE":"no","NAME1":"Siikajoki","NAME2":"Siikajoki","POP":"5466","AREA":"1653960000"},{"COUNTRY_CODE":"FI","NUTS3":"FI1D2","LAU1":"112","LAU2":"749","_CHANGE":"no","NAME1":"Siilinjärvi","NAME2":"Siilinjärvi","POP":"21794","AREA":"507810000"},{"COUNTRY_CODE":"FI","NUTS3":"FI1D7","LAU1":"192","LAU2":"751","_CHANGE":"no","NAME1":"Simo","NAME2":"Simo","POP":"3238","AREA":"2086310000"},{"COUNTRY_CODE":"FI","NUTS3":"FI1B1","LAU1":"011","LAU2":"753","_CHANGE":"no","NAME1":"Sipoo","NAME2":"Sibbo","POP":"19399","AREA":"698600000"},{"COUNTRY_CODE":"FI","NUTS3":"FI1B1","LAU1":"011","LAU2":"755","_CHANGE":"no","NAME1":"Siuntio","NAME2":"Sjundeå","POP":"6182","AREA":"266110000"},{"COUNTRY_CODE":"FI","NUTS3":"FI1D7","LAU1":"197","LAU2":"758","_CHANGE":"no","NAME1":"Sodankylä","NAME2":"Sodankylä","POP":"8782","AREA":"12415500000"},{"COUNTRY_CODE":"FI","NUTS3":"FI194","LAU1":"146","LAU2":"759","_CHANGE":"no","NAME1":"Soini","NAME2":"Soini","POP":"2224","AREA":"574220000"},{"COUNTRY_CODE":"FI","NUTS3":"FI1C1","LAU1":"022","LAU2":"761","_CHANGE":"no","NAME1":"Somero","NAME2":"Somero","POP":"9093","AREA":"697680000"},{"COUNTRY_CODE":"FI","NUTS3":"FI1D2","LAU1":"111","LAU2":"762","_CHANGE":"no","NAME1":"Sonkajärvi","NAME2":"Sonkajärvi","POP":"4278","AREA":"1576750000"},{"COUNTRY_CODE":"FI","NUTS3":"FI1D4","LAU1":"182","LAU2":"765","_CHANGE":"no","NAME1":"Sotkamo","NAME2":"Sotkamo","POP":"10523","AREA":"2951870000"},{"COUNTRY_CODE":"FI","NUTS3":"FI200","LAU1":"213","LAU2":"766","_CHANGE":"no","NAME1":"Sottunga","NAME2":"Sottunga","POP":"99","AREA":"342440000"},{"COUNTRY_CODE":"FI","NUTS3":"FI1D1","LAU1":"103","LAU2":"768","_CHANGE":"no","NAME1":"Sulkava","NAME2":"Sulkava","POP":"2724","AREA":"769200000"},{"COUNTRY_CODE":"FI","NUTS3":"FI200","LAU1":"212","LAU2":"771","_CHANGE":"no","NAME1":"Sund","NAME2":"Sund","POP":"1031","AREA":"184310000"},{"COUNTRY_CODE":"FI","NUTS3":"FI1D4","LAU1":"181","LAU2":"777","_CHANGE":"no","NAME1":"Suomussalmi","NAME2":"Suomussalmi","POP":"8336","AREA":"5857620000"},{"COUNTRY_CODE":"FI","NUTS3":"FI1D2","LAU1":"115","LAU2":"778","_CHANGE":"no","NAME1":"Suonenjoki","NAME2":"Suonenjoki","POP":"7390","AREA":"862340000"},{"COUNTRY_CODE":"FI","NUTS3":"FI1C3","LAU1":"071","LAU2":"781","_CHANGE":"no","NAME1":"Sysmä","NAME2":"Sysmä","POP":"4040","AREA":"936180000"},{"COUNTRY_CODE":"FI","NUTS3":"FI196","LAU1":"041","LAU2":"783","_CHANGE":"1/1/16","NAME1":"Säkylä","NAME2":"Säkylä","POP":"7070","AREA":"527710000"},{"COUNTRY_CODE":"FI","NUTS3":"FI1D4","LAU1":"173","LAU2":"785","_CHANGE":"no","NAME1":"Vaala","NAME2":"Vaala","POP":"3074","AREA":"1764030000"},{"COUNTRY_CODE":"FI","NUTS3":"FI197","LAU1":"068","LAU2":"790","_CHANGE":"no","NAME1":"Sastamala","NAME2":"Sastamala","POP":"25220","AREA":"1531740000"},{"COUNTRY_CODE":"FI","NUTS3":"FI1D6","LAU1":"175","LAU2":"791","_CHANGE":"no","NAME1":"Siikalatva","NAME2":"Siikalatva","POP":"5677","AREA":"2229210000"},{"COUNTRY_CODE":"FI","NUTS3":"FI1C5","LAU1":"091","LAU2":"831","_CHANGE":"no","NAME1":"Taipalsaari","NAME2":"Taipalsaari","POP":"4815","AREA":"761940000"},{"COUNTRY_CODE":"FI","NUTS3":"FI1D6","LAU1":"178","LAU2":"832","_CHANGE":"no","NAME1":"Taivalkoski","NAME2":"Taivalkoski","POP":"4199","AREA":"2650660000"},{"COUNTRY_CODE":"FI","NUTS3":"FI1C1","LAU1":"024","LAU2":"833","_CHANGE":"no","NAME1":"Taivassalo","NAME2":"Tövsala","POP":"1633","AREA":"217730000"},{"COUNTRY_CODE":"FI","NUTS3":"FI1C2","LAU1":"053","LAU2":"834","_CHANGE":"no","NAME1":"Tammela","NAME2":"Tammela","POP":"6280","AREA":"715140000"},{"COUNTRY_CODE":"FI","NUTS3":"FI197","LAU1":"064","LAU2":"837","_CHANGE":"no","NAME1":"Tampere","NAME2":"Tammerfors","POP":"225118","AREA":"689590000"},{"COUNTRY_CODE":"FI","NUTS3":"FI1D2","LAU1":"115","LAU2":"844","_CHANGE":"no","NAME1":"Tervo","NAME2":"Tervo","POP":"1608","AREA":"494300000"},{"COUNTRY_CODE":"FI","NUTS3":"FI1D7","LAU1":"192","LAU2":"845","_CHANGE":"no","NAME1":"Tervola","NAME2":"Tervola","POP":"3195","AREA":"1592030000"},{"COUNTRY_CODE":"FI","NUTS3":"FI194","LAU1":"141","LAU2":"846","_CHANGE":"no","NAME1":"Teuva","NAME2":"Östermark","POP":"5482","AREA":"556050000"},{"COUNTRY_CODE":"FI","NUTS3":"FI1D3","LAU1":"124","LAU2":"848","_CHANGE":"no","NAME1":"Tohmajärvi","NAME2":"Tohmajärvi","POP":"4738","AREA":"895360000"},{"COUNTRY_CODE":"FI","NUTS3":"FI1D5","LAU1":"161","LAU2":"849","_CHANGE":"no","NAME1":"Toholampi","NAME2":"Toholampi","POP":"3311","AREA":"616880000"},{"COUNTRY_CODE":"FI","NUTS3":"FI193","LAU1":"131","LAU2":"850","_CHANGE":"no","NAME1":"Toivakka","NAME2":"Toivakka","POP":"2431","AREA":"413940000"},{"COUNTRY_CODE":"FI","NUTS3":"FI1D7","LAU1":"192","LAU2":"851","_CHANGE":"no","NAME1":"Tornio","NAME2":"Torneå","POP":"22199","AREA":"1348830000"},{"COUNTRY_CODE":"FI","NUTS3":"FI1C1","LAU1":"023","LAU2":"853","_CHANGE":"no","NAME1":"Turku","NAME2":"Åbo","POP":"185908","AREA":"306360000"},{"COUNTRY_CODE":"FI","NUTS3":"FI1D7","LAU1":"193","LAU2":"854","_CHANGE":"no","NAME1":"Pello","NAME2":"Pello","POP":"3623","AREA":"1863720000"},{"COUNTRY_CODE":"FI","NUTS3":"FI1D2","LAU1":"113","LAU2":"857","_CHANGE":"no","NAME1":"Tuusniemi","NAME2":"Tuusniemi","POP":"2719","AREA":"699430000"},{"COUNTRY_CODE":"FI","NUTS3":"FI1B1","LAU1":"011","LAU2":"858","_CHANGE":"no","NAME1":"Tuusula","NAME2":"Tusby","POP":"38459","AREA":"225460000"},{"COUNTRY_CODE":"FI","NUTS3":"FI1D6","LAU1":"171","LAU2":"859","_CHANGE":"no","NAME1":"Tyrnävä","NAME2":"Tyrnävä","POP":"6793","AREA":"494860000"},{"COUNTRY_CODE":"FI","NUTS3":"FI196","LAU1":"043","LAU2":"886","_CHANGE":"no","NAME1":"Ulvila","NAME2":"Ulvsby","POP":"13352","AREA":"422510000"},{"COUNTRY_CODE":"FI","NUTS3":"FI197","LAU1":"063","LAU2":"887","_CHANGE":"no","NAME1":"Urjala","NAME2":"Urjala","POP":"4928","AREA":"505370000"},{"COUNTRY_CODE":"FI","NUTS3":"FI1D6","LAU1":"173","LAU2":"889","_CHANGE":"no","NAME1":"Utajärvi","NAME2":"Utajärvi","POP":"2861","AREA":"1736700000"},{"COUNTRY_CODE":"FI","NUTS3":"FI1D7","LAU1":"197","LAU2":"890","_CHANGE":"no","NAME1":"Utsjoki","NAME2":"Utsjoki","POP":"1250","AREA":"5372000000"},{"COUNTRY_CODE":"FI","NUTS3":"FI193","LAU1":"131","LAU2":"892","_CHANGE":"no","NAME1":"Uurainen","NAME2":"Uurainen","POP":"3666","AREA":"372270000"},{"COUNTRY_CODE":"FI","NUTS3":"FI195","LAU1":"154","LAU2":"893","_CHANGE":"no","NAME1":"Uusikaarlepyy","NAME2":"Nykarleby","POP":"7564","AREA":"1675200000"},{"COUNTRY_CODE":"FI","NUTS3":"FI1C1","LAU1":"024","LAU2":"895","_CHANGE":"no","NAME1":"Uusikaupunki","NAME2":"Nystad","POP":"15510","AREA":"1932400000"},{"COUNTRY_CODE":"FI","NUTS3":"FI195","LAU1":"152","LAU2":"905","_CHANGE":"no","NAME1":"Vaasa","NAME2":"Vasa","POP":"67619","AREA":"575130000"},{"COUNTRY_CODE":"FI","NUTS3":"FI197","LAU1":"063","LAU2":"908","_CHANGE":"no","NAME1":"Valkeakoski","NAME2":"Valkeakoski","POP":"21332","AREA":"372030000"},{"COUNTRY_CODE":"FI","NUTS3":"FI1D3","LAU1":"125","LAU2":"911","_CHANGE":"no","NAME1":"Valtimo","NAME2":"Valtimo","POP":"2324","AREA":"838070000"},{"COUNTRY_CODE":"FI","NUTS3":"FI1D2","LAU1":"114","LAU2":"915","_CHANGE":"no","NAME1":"Varkaus","NAME2":"Varkaus","POP":"21638","AREA":"524480000"},{"COUNTRY_CODE":"FI","NUTS3":"FI1C1","LAU1":"024","LAU2":"918","_CHANGE":"no","NAME1":"Vehmaa","NAME2":"Vehmaa","POP":"2276","AREA":"202090000"},{"COUNTRY_CODE":"FI","NUTS3":"FI1D2","LAU1":"115","LAU2":"921","_CHANGE":"no","NAME1":"Vesanto","NAME2":"Vesanto","POP":"2191","AREA":"569800000"},{"COUNTRY_CODE":"FI","NUTS3":"FI197","LAU1":"064","LAU2":"922","_CHANGE":"1/1/16","NAME1":"Vesilahti","NAME2":"Vesilahti","POP":"4489","AREA":"353940000"},{"COUNTRY_CODE":"FI","NUTS3":"FI1D5","LAU1":"161","LAU2":"924","_CHANGE":"no","NAME1":"Veteli","NAME2":"Vetil","POP":"3302","AREA":"520910000"},{"COUNTRY_CODE":"FI","NUTS3":"FI1D2","LAU1":"111","LAU2":"925","_CHANGE":"no","NAME1":"Vieremä","NAME2":"Vieremä","POP":"3757","AREA":"973390000"},{"COUNTRY_CODE":"FI","NUTS3":"FI1B1","LAU1":"011","LAU2":"927","_CHANGE":"no","NAME1":"Vihti","NAME2":"Vichtis","POP":"28919","AREA":"567060000"},{"COUNTRY_CODE":"FI","NUTS3":"FI193","LAU1":"138","LAU2":"931","_CHANGE":"no","NAME1":"Viitasaari","NAME2":"Viitasaari","POP":"6666","AREA":"1589130000"},{"COUNTRY_CODE":"FI","NUTS3":"FI194","LAU1":"146","LAU2":"934","_CHANGE":"no","NAME1":"Vimpeli","NAME2":"Vimpeli","POP":"3073","AREA":"328790000"},{"COUNTRY_CODE":"FI","NUTS3":"FI1C4","LAU1":"082","LAU2":"935","_CHANGE":"no","NAME1":"Virolahti","NAME2":"Virolahti","POP":"3347","AREA":"558920000"},{"COUNTRY_CODE":"FI","NUTS3":"FI197","LAU1":"069","LAU2":"936","_CHANGE":"no","NAME1":"Virrat","NAME2":"Virdois","POP":"7002","AREA":"1299080000"},{"COUNTRY_CODE":"FI","NUTS3":"FI200","LAU1":"213","LAU2":"941","_CHANGE":"no","NAME1":"Vårdö","NAME2":"Vårdö","POP":"441","AREA":"572560000"},{"COUNTRY_CODE":"FI","NUTS3":"FI195","LAU1":"152","LAU2":"946","_CHANGE":"no","NAME1":"Vöyri","NAME2":"Vörå","POP":"6714","AREA":"1499900000"},{"COUNTRY_CODE":"FI","NUTS3":"FI1D7","LAU1":"193","LAU2":"976","_CHANGE":"no","NAME1":"Ylitornio","NAME2":"Övertorneå","POP":"4291","AREA":"2212490000"},{"COUNTRY_CODE":"FI","NUTS3":"FI1D6","LAU1":"177","LAU2":"977","_CHANGE":"no","NAME1":"Ylivieska","NAME2":"Ylivieska","POP":"15039","AREA":"573190000"},{"COUNTRY_CODE":"FI","NUTS3":"FI197","LAU1":"064","LAU2":"980","_CHANGE":"no","NAME1":"Ylöjärvi","NAME2":"Ylöjärvi","POP":"32738","AREA":"1324140000"},{"COUNTRY_CODE":"FI","NUTS3":"FI1C2","LAU1":"053","LAU2":"981","_CHANGE":"no","NAME1":"Ypäjä","NAME2":"Ypäjä","POP":"2411","AREA":"183250000"},{"COUNTRY_CODE":"FI","NUTS3":"FI194","LAU1":"144","LAU2":"989","_CHANGE":"no","NAME1":"Ähtäri","NAME2":"Etseri","POP":"6068","AREA":"910880000"},{"COUNTRY_CODE":"FI","NUTS3":"FI193","LAU1":"135","LAU2":"992","_CHANGE":"no","NAME1":"Äänekoski","NAME2":"Äänekoski","POP":"19646","AREA":"1138380000"}]
